{"books": [{"title": "B\u1ea1ch D\u1ea1 H\u00e0nh", "authors": "nhi\u1ec1u t\u00e1c gi\u1ea3", "genre": "t\u00ecnh c\u1ea3m", "year": "1999", "pages": "222", "image_path": "C:/Users/chuon/Desktop/Book-store/images/CHUONG.png", "chapter": "13", "content_url": "https://nhasachmienphi.com/doc-online/bach-da-hanh-311518"}, {"title": "T\u1ef1 h\u1ecdc ti\u1ebfng anh hi\u1ec7u qu\u1ea3", "authors": "Nguy\u1ec5n Th\u1ecb H\u00e0 B\u1eafc", "genre": "H\u1ecdc Ngo\u1ea1i Ng\u1eef", "year": "2013", "pages": "211", "image_path": "images\\books\\english.jpg", "chapter": "7", "content_url": "https://nhasachmienphi.com/doc-online/tu-hoc-tieng-anh-hieu-qua-316671"}, {"title": "C\u00f4ng Ngh\u1ec7 Blockchain", "authors": "Nhi\u1ec1u t\u00e1c gi\u1ea3", "genre": "C\u00f4ng Ngh\u1ec7 Th\u00f4ng Tin", "year": "2017", "pages": "100", "image_path": "images\\books\\blockchain.jpg", "chapter": "8", "content_url": "https://nhasachmienphi.com/doc-online/cong-nghe-blockchain-167458"}, {"title": "Cu\u1ed9c Ng\u00e3 Gi\u00e1 C\u1ee7a Nh\u00e0 T\u1ef7 Ph\u00fa", "authors": "Barbara Dunlop", "genre": "Ti\u1ec3u Thuy\u1ebft Ph\u01b0\u01a1ng T\u00e2y", "year": "1997", "pages": "270", "image_path": "images\\books\\typhu.jpg", "chapter": "12", "content_url": "https://nhasachmienphi.com/doc-online/cuoc-nga-gia-cua-nha-ty-phu-234269"}, {"title": "Thi\u1ebfu N\u1eef \u0110\u00e1nh C\u1edd V\u00e2y", "authors": "S\u01a1n T\u00e1p", "genre": "Ti\u1ec3u Thuy\u1ebft Trung hoa", "year": "2003", "pages": "312", "image_path": "images\\books\\covay.jpg", "chapter": "9", "content_url": "https://nhasachmienphi.com/doc-online/thieu-nu-danh-co-vay-234748"}, {"title": "Th\u00fa T\u1ed9i", "authors": "Minato Kanae", "genre": "Trinh Th\u00e1m - H\u00ecnh S\u1ef1", "year": "2002", "pages": "250", "image_path": "images\\books\\thutoi.jpg", "chapter": "6", "content_url": "https://nhasachmienphi.com/doc-online/thu-toi-312632"}, {"title": "Ph\u00eda Sau Nghi Can X", "authors": "Higashino Keigo", "genre": "Trinh Th\u00e1m - H\u00ecnh S\u1ef1", "year": "2005", "pages": "250", "image_path": "images\\books\\x.jpg", "chapter": "19", "content_url": "https://nhasachmienphi.com/doc-online/phia-sau-nghi-can-x-312142"}, {"title": "Lu\u1eadt S\u1ef1 Nh\u00ed", "authors": "John Grisham", "genre": "Trinh Th\u00e1m - H\u00ecnh S\u1ef1", "year": "2005", "pages": "250", "image_path": "images\\books\\lsn.jpg", "chapter": "22", "content_url": "https://nhasachmienphi.com/doc-online/luat-su-nhi-314835"}]}